embexpr/__init__.py
embexpr/__version__.py
embexpr/error.py
embexpr/expr.py
embexpr-1.1.1.dist-info/LICENSE
embexpr-1.1.1.dist-info/METADATA
embexpr-1.1.1.dist-info/WHEEL
embexpr-1.1.1.dist-info/top_level.txt
embexpr-1.1.1.dist-info/RECORD
